assignment 2/5.registers/registers.v
// Ayush Kumar 17CO111
//Ranjana K 17CO134




// 1bit D FlipFlop with enable and +ve edge triggered
module register(output reg q,input d,input enable,input clock);
always @(posedge clock)
begin
	if(enable) begin
		q=d;
	end
end
endmodule

// 32bit D FlipFlop with enable and +ve edge triggered
module register32(output reg[31:0] q,input[31:0] d,input enable,input clock);
always @(posedge clock)
begin
	if(enable) begin
		q=d;
	end
end
endmodule

// Set R0=0
module register32zero(output wire[31:0] q,input[31:0] d,input enable,input clock);
	assign q=32'b0;
endmodule

// MUX
module mux32to1by32(output[31:0] out,input[4:0] address,input[31:0] input0,input1,input2,input3,input4,input5,input6,input7,
																	input8,input9,input10,input11,input12,input13,input14,input15,
																	input16,input17,input18,input19,input20,input21,input22,input23,
																	input24,input25,input26,input27,input28,input29,input30,input31);
	wire[31:0] mux[31:0];
	assign mux[0]=input0;
	assign mux[1]=input1;
	assign mux[2]=input2;
	assign mux[3]=input3;
	assign mux[4]=input4;
	assign mux[5]=input5;
	assign mux[6]=input6;
	assign mux[7]=input7;
	assign mux[8]=input8;
	assign mux[9]=input9;
	assign mux[10]=input10;
	assign mux[11]=input11;
	assign mux[12]=input12;
	assign mux[13]=input13;
	assign mux[14]=input14;
	assign mux[15]=input15;
	assign mux[16]=input16;
	assign mux[17]=input17;
	assign mux[18]=input18;
	assign mux[19]=input19;
	assign mux[20]=input20;
	assign mux[21]=input21;
	assign mux[22]=input22;
	assign mux[23]=input23;
	assign mux[24]=input24;
	assign mux[25]=input25;
	assign mux[26]=input26;
	assign mux[27]=input27;
	assign mux[28]=input28;
	assign mux[29]=input29;
	assign mux[30]=input30;
	assign mux[31]=input31;
	assign out=mux[address];
endmodule

assignment 2/5.registers/decoders.v
//Ayush Kumar 17CO111
//Ranjana K 17CO134


module decoder(output[31:0] out,input enable,input[4:0] address);
	assign out= enable<<address;
endmodule

assignment 2/5.registers/regfile.v
//Ayush Kumar 17CO111
//Ranjana K 17CO134

`include "decoders.v"
`include "registers.v"

module regfile(output[31:0] ReadData1, 	// 1st Register Read
			   output[31:0] ReadData2,	// 2nd Register Read
			   input[31:0] WriteData,	// Data to write to register
			   input[4:0] ReadRegister1,// Address to read 1st Register
			   input[4:0] ReadRegister2,// Address to read 2nd Register
               input[4:0] WriteRegister,//Address of register to write
			   input RegWrite,			// Enable to write to register
			   input clock);
			   
	wire[31:0] DecoderOut;
	wire[31:0] RegOut[31:0];
	
	// Decoder for write enable
	decoder decoder1_32(DecoderOut,RegWrite,WriteRegister);
	register32zero register32_0(RegOut[0],WriteData,DecoderOut[0],clock);
	
	// Registers
	generate
		genvar i;
		for(i=1;i<32;i=i+1)
		begin
				register32 register_32(RegOut[i],WriteData,DecoderOut[i],clock);
		end
	endgenerate
	
	mux32to1by32 mux1(ReadData1,ReadRegister1,RegOut[0],RegOut[1],RegOut[2],RegOut[3],
											 RegOut[4],RegOut[5],RegOut[6],RegOut[7],
											 RegOut[8],RegOut[9],RegOut[10],RegOut[11],
											 RegOut[12],RegOut[13],RegOut[14],RegOut[15],
											 RegOut[16],RegOut[17],RegOut[18],RegOut[19],
											 RegOut[20],RegOut[21],RegOut[22],RegOut[23],
											 RegOut[24],RegOut[25],RegOut[26],RegOut[27],
											 RegOut[28],RegOut[29],RegOut[30],RegOut[31]);
											 
	mux32to1by32 mux2(ReadData2,ReadRegister2,RegOut[0],RegOut[1],RegOut[2],RegOut[3],
											 RegOut[4],RegOut[5],RegOut[6],RegOut[7],
											 RegOut[8],RegOut[9],RegOut[10],RegOut[11],
											 RegOut[12],RegOut[13],RegOut[14],RegOut[15],
											 RegOut[16],RegOut[17],RegOut[18],RegOut[19],
											 RegOut[20],RegOut[21],RegOut[22],RegOut[23],
											 RegOut[24],RegOut[25],RegOut[26],RegOut[27],
											 RegOut[28],RegOut[29],RegOut[30],RegOut[31]);
											 
endmodule

assignment 2/5.registers/registers_tb.v
//Ayush Kumar 17CO111
//Ranjana K 17CO134


`include "regfile.v"

module testbench;

  wire[31:0] ReadData1;	
  wire[31:0] ReadData2;	
  wire[31:0] WriteData;	
  wire[4:0]	ReadRegister1;	
  wire[4:0]	ReadRegister2;	
  wire[4:0]	WriteRegister;  
  wire RegWrite;	
  wire clock;		

  reg begintest;

	// DUT = Device Under Test
  regfile DUT
  (
    .ReadData1(ReadData1),
    .ReadData2(ReadData2),
    .WriteData(WriteData),
    .ReadRegister1(ReadRegister1),
    .ReadRegister2(ReadRegister2),
    .WriteRegister(WriteRegister),
    .RegWrite(RegWrite),
    .clock(clock)
  );

  testbench_register tester
  (
    .begintest(begintest),
    .endtest(endtest), 
    .ReadData1(ReadData1),
    .ReadData2(ReadData2),
    .WriteData(WriteData), 
    .ReadRegister1(ReadRegister1), 
    .ReadRegister2(ReadRegister2),
    .WriteRegister(WriteRegister),
    .RegWrite(RegWrite), 
    .clock(clock)
  );

  initial begin
    begintest=0;
    #10;
    begintest=1;
    #100;
  end
endmodule

module testbench_register
(
input begintest,
output reg endtest,

input[31:0]		ReadData1,
input[31:0]		ReadData2,
output reg[31:0]	WriteData,
output reg[4:0]		ReadRegister1,
output reg[4:0]		ReadRegister2,
output reg[4:0]		WriteRegister,
output reg		RegWrite,
output reg		clock
);

  initial
     begin
        $dumpfile("reg.vcd");
        $dumpvars(0,testbench_register);
	end
 
 // Initializing the register signals
 initial begin
    WriteData=32'd0;
    ReadRegister1=5'd0;
    ReadRegister2=5'd0;
    WriteRegister=5'd0;
    RegWrite=0;
    clock=0;
  end

  always @(posedge begintest) begin
    endtest = 0;
    #10
		//Test1: Write R2<=38
		  WriteRegister = 5'd2;
		  WriteData = 32'd38;
		  RegWrite = 1;
		  ReadRegister1 = 5'd2;
		  ReadRegister2 = 5'd2;
		  #5 clock=1; #5 clock=0;
			$display("Writing 38 to register2");
			$display("WriteRegister=%d , WriteData=%-3d , RegWrite=%b, ReadRegister1=%d, ReadRegister2=%-3d, ReadData1=%-3d ReadData2=%-3d\n",WriteRegister,WriteData,RegWrite,ReadRegister1,ReadRegister2,ReadData1,ReadData2);
		
		//Test2: Write R2<=15
		  WriteRegister = 5'd2;
		  WriteData = 32'd15;
		  RegWrite = 1;
		  ReadRegister1 = 5'd2;
		  ReadRegister2 = 5'd2;
		  #5 clock=1; #5 clock=0;
			$display("Writing 15 to register2");
			$display("WriteRegister=%d , WriteData=%-3d , RegWrite=%b, ReadRegister1=%d, ReadRegister2=%d, ReadData1=%-3d ReadData2=%-3d\n",WriteRegister,WriteData,RegWrite,ReadRegister1,ReadRegister2,ReadData1,ReadData2);
  
		//Test3: Write R3<=16, but RegWrite=0, so should not be written
		  WriteRegister = 5'd3;
		  WriteData = 32'd16;
		  RegWrite = 0;
		  ReadRegister1 = 5'd3;
		  ReadRegister2 = 5'd3;
		  #5 clock=1; #5 clock=0;
			$display("As RegWrite=0, no data should be written");
			$display("WriteRegister=%d , WriteData=%-3d , RegWrite=%b, ReadRegister1=%d, ReadRegister2=%d, ReadData1=%-2d ReadData2=%-3d\n",WriteRegister,WriteData,RegWrite,ReadRegister1,ReadRegister2,ReadData1,ReadData2);
		  
		//Test4: Write R4<=987
		  WriteRegister = 5'd4;
		  WriteData = 32'd987;
		  RegWrite = 1;
		  ReadRegister1 = 5'd8;
		  ReadRegister2 = 5'd31;
		  #5 clock=1; #5 clock=0;
			$display("Writing 987 to register4, ReadData from register8 and register31");
			$display("WriteRegister=%d , WriteData=%-3d , RegWrite=%b, ReadRegister1=%d, ReadRegister2=%d, ReadData1=%-3d ReadData2=%-3d\n",WriteRegister,WriteData,RegWrite,ReadRegister1,ReadRegister2,ReadData1,ReadData2);
		  
  
		//Test5: Try to write R0<=456 (Should not be written)
		  WriteRegister = 5'd0;
		  WriteData = 32'd456;
		  RegWrite = 1;
		  ReadRegister1 = 5'd0;
		  ReadRegister2 = 5'd0;
		  #5 clock=1; #5 clock=0;
			$display("Write 456 to Register0, should not be written");
			$display("WriteRegister=%d , WriteData=%-3d , RegWrite=%b, ReadRegister1=%d, ReadRegister2=%d, ReadData1=%-3d ReadData2=%-3d\n",WriteRegister,WriteData,RegWrite,ReadRegister1,ReadRegister2,ReadData1,ReadData2);
		 
		 //Test6: Write R17<=810 & R2<=323
		  WriteRegister = 5'd17;
		  WriteData = 32'd810;
		  RegWrite = 1;
		  #5 clock=1; #5 clock=0;
				
		  WriteRegister = 5'd2;
		  WriteData = 32'd323;
		  RegWrite = 1;
		  ReadRegister1 = 5'd17;
	      ReadRegister2 = 5'd2;
		  #5 clock=1; #5 clock=0;
			$display("Write 810 to Register17 and 323 to Register2");
			$display("WriteRegister=%d , WriteData=%-3d , RegWrite=%b, ReadRegister1=%d, ReadRegister2=%d, ReadData1=%-3d ReadData2=%-3d\n",WriteRegister,WriteData,RegWrite,ReadRegister1,ReadRegister2,ReadData1,ReadData2);
   
   #5
		endtest = 1;

end
endmodule

assignment 2/5.registers/reg.vcd
$date
	Thu Oct 25 18:46:44 2018
$end
$version
	Icarus Verilog
$end
$timescale
	1s
$end
$scope module testbench $end
$scope module tester $end
$var wire 32 ! ReadData1 [31:0] $end
$var wire 32 " ReadData2 [31:0] $end
$var wire 1 # begintest $end
$var reg 5 $ ReadRegister1 [4:0] $end
$var reg 5 % ReadRegister2 [4:0] $end
$var reg 1 & RegWrite $end
$var reg 32 ' WriteData [31:0] $end
$var reg 5 ( WriteRegister [4:0] $end
$var reg 1 ) clock $end
$var reg 1 * endtest $end
$upscope $end
$upscope $end
$enddefinitions $end
#0
$dumpvars
x*
0)
b0 (
b0 '
0&
b0 %
b0 $
0#
b0 "
b0 !
$end
#10
0*
1#
#20
bx "
b10 %
bx !
b10 $
1&
b100110 '
b10 (
#25
b100110 !
b100110 "
1)
#30
b1111 '
0)
#35
b1111 !
b1111 "
1)
#40
bx "
b11 %
bx !
b11 $
0&
b10000 '
b11 (
0)
#45
1)
#50
b11111 %
b1000 $
1&
b1111011011 '
b100 (
0)
#55
1)
#60
b0 "
b0 %
b0 !
b0 $
b111001000 '
b0 (
0)
#65
1)
#70
b1100101010 '
b10001 (
0)
#75
1)
#80
b1111 "
b10 %
b1100101010 !
b10001 $
b101000011 '
b10 (
0)
#85
b101000011 "
1)
#90
0)
#95
1*
